materia/.gitignore
materia/utils/__init__.py
materia/utils/math.py
materia/utils/utils.py
materia_utils-1.0.0.dist-info/LICENSE
materia_utils-1.0.0.dist-info/WHEEL
materia_utils-1.0.0.dist-info/METADATA
materia_utils-1.0.0.dist-info/RECORD
