Metadata-Version: 2.1
Name: materia-utils
Version: 1.0.0
Summary: Utilities for atomistic simulations of materials through Materia.
Home-page: https://github.com/kijanac/luz
License: MIT
Author: Ki-Jana Carter
Author-email: kijana@mit.edu
Requires-Python: >=3.9,<3.11
Classifier: License :: OSI Approved :: MIT License
Classifier: Programming Language :: Python :: 3
Classifier: Programming Language :: Python :: 3.10
Classifier: Programming Language :: Python :: 3.9
Requires-Dist: numpy (>=1.19.4,<2.0.0)
Requires-Dist: scipy (>=1.5.4,<2.0.0)
Project-URL: Repository, https://github.com/kijanac/luz
